README.md
setup.cfg
setup.py
fedex_python/__init__.py
fedex_python/base.py
fedex_python/client.py
fedex_python.egg-info/PKG-INFO
fedex_python.egg-info/SOURCES.txt
fedex_python.egg-info/dependency_links.txt
fedex_python.egg-info/requires.txt
fedex_python.egg-info/top_level.txt
fedex_python/components/__init__.py
fedex_python/components/authentication.py
fedex_python/components/base.py
fedex_python/components/common.py
fedex_python/components/enums.py
fedex_python/components/pickup_components.py
fedex_python/components/rate_components.py
fedex_python/components/ship_components.py
fedex_python/components/track_components.py
fedex_python/services/__init__.py
fedex_python/services/pickup.py
fedex_python/services/rate.py
fedex_python/services/ship.py
fedex_python/services/track.py
fedex_python/wsdl/pickup_17.wsdl
fedex_python/wsdl/rate_28.wsdl
fedex_python/wsdl/ship_25.wsdl
fedex_python/wsdl/track_16.wsdl
fedex_python/wsdl/test/pickup_17.wsdl
fedex_python/wsdl/test/rate_28.wsdl
fedex_python/wsdl/test/ship_25.wsdl
fedex_python/wsdl/test/track_16.wsdl