Metadata-Version: 2.1
Name: fedex-python
Version: 0.0.5
Summary: NOT official module for use fedex web services with python
Home-page: https://github.com/sr1871/fedex-python
Author: Sergio Alvarado
Author-email: sergioal18v@gmail.com
License: UNKNOWN
Keywords: FedEx,python
Platform: UNKNOWN
Classifier: Programming Language :: Python :: 3
Classifier: License :: OSI Approved :: MIT License
Classifier: Operating System :: OS Independent
